carmine/__about__.py
carmine/__init__.py
carmine/__main__.py
carmine/cli.py
carmine/exceptions.py
tests/__init__.py
sh40_carmine-0.3.5.dist-info/METADATA
sh40_carmine-0.3.5.dist-info/WHEEL
sh40_carmine-0.3.5.dist-info/entry_points.txt
sh40_carmine-0.3.5.dist-info/licenses/LICENSE.txt
sh40_carmine-0.3.5.dist-info/RECORD
