Metadata-Version: 2.1
Name: sh40-carmine
Version: 0.3.5
Summary: The no-boilerplate CLI library powered by Python's introspection.
Project-URL: Documentation, https://github.com/shade40/carmine#readme
Project-URL: Issues, https://github.com/shade40/carmine/issues
Project-URL: Source, https://github.com/shade40/carmine
Author-email: bczsalba <bczsalba@gmail.com>
License-Expression: MIT
License-File: LICENSE.txt
Classifier: Development Status :: 4 - Beta
Classifier: Programming Language :: Python
Classifier: Programming Language :: Python :: 3.7
Classifier: Programming Language :: Python :: 3.8
Classifier: Programming Language :: Python :: 3.9
Classifier: Programming Language :: Python :: 3.10
Classifier: Programming Language :: Python :: 3.11
Classifier: Programming Language :: Python :: Implementation :: CPython
Classifier: Programming Language :: Python :: Implementation :: PyPy
Requires-Python: >=3.8
Requires-Dist: griffe
Requires-Dist: sh40-slate
Requires-Dist: sh40-zenith
